jupyterlab_js_logs/__init__.py
jupyterlab_js_logs/_version.py
jupyterlab_js_logs/labextension/package.json
jupyterlab_js_logs/labextension/static/534.8861373ce26e12d773ea.js
jupyterlab_js_logs/labextension/static/609.74c56e7b95cc5ef303cc.js
jupyterlab_js_logs/labextension/static/remoteEntry.df98680eeff3bef5ddf0.js
jupyterlab_js_logs/labextension/static/style.js
jupyterlab_js_logs-0.2.6.data/data/share/jupyter/labextensions/jupyterlab-js-logs/install.json
jupyterlab_js_logs-0.2.6.data/data/share/jupyter/labextensions/jupyterlab-js-logs/package.json
jupyterlab_js_logs-0.2.6.data/data/share/jupyter/labextensions/jupyterlab-js-logs/static/534.8861373ce26e12d773ea.js
jupyterlab_js_logs-0.2.6.data/data/share/jupyter/labextensions/jupyterlab-js-logs/static/609.74c56e7b95cc5ef303cc.js
jupyterlab_js_logs-0.2.6.data/data/share/jupyter/labextensions/jupyterlab-js-logs/static/remoteEntry.df98680eeff3bef5ddf0.js
jupyterlab_js_logs-0.2.6.data/data/share/jupyter/labextensions/jupyterlab-js-logs/static/style.js
jupyterlab_js_logs-0.2.6.dist-info/LICENSE
jupyterlab_js_logs-0.2.6.dist-info/METADATA
jupyterlab_js_logs-0.2.6.dist-info/WHEEL
jupyterlab_js_logs-0.2.6.dist-info/top_level.txt
jupyterlab_js_logs-0.2.6.dist-info/RECORD
