Metadata-Version: 2.1
Name: jupyterlab-js-logs
Version: 0.2.6
Summary: JupyterLab extension to show the js logs from the browser dev tools console
Home-page: https://github.com/QuantStack/jupyterlab-js-logs
Author: jupyterlab-js-logs contributors
Author-email: 
License: BSD-3-Clause
Keywords: Jupyter,JupyterLab,JupyterLab3
Platform: Linux
Platform: Mac OS X
Platform: Windows
Classifier: License :: OSI Approved :: BSD License
Classifier: Programming Language :: Python
Classifier: Programming Language :: Python :: 3
Classifier: Programming Language :: Python :: 3.6
Classifier: Programming Language :: Python :: 3.7
Classifier: Programming Language :: Python :: 3.8
Classifier: Programming Language :: Python :: 3.9
Classifier: Framework :: Jupyter
Requires-Python: >=3.6
License-File: LICENSE
